ausmints_calculator/__init__.py
ausmints_calculator/calculator.py
ausmints_calculator/.mypy_cache/.gitignore
ausmints_calculator/.mypy_cache/CACHEDIR.TAG
ausmints_calculator/.mypy_cache/3.9/@plugins_snapshot.json
ausmints_calculator/.mypy_cache/3.9/_ast.data.json
ausmints_calculator/.mypy_cache/3.9/_ast.meta.json
ausmints_calculator/.mypy_cache/3.9/_importlib_modulespec.data.json
ausmints_calculator/.mypy_cache/3.9/_importlib_modulespec.meta.json
ausmints_calculator/.mypy_cache/3.9/abc.data.json
ausmints_calculator/.mypy_cache/3.9/abc.meta.json
ausmints_calculator/.mypy_cache/3.9/array.data.json
ausmints_calculator/.mypy_cache/3.9/array.meta.json
ausmints_calculator/.mypy_cache/3.9/ast.data.json
ausmints_calculator/.mypy_cache/3.9/ast.meta.json
ausmints_calculator/.mypy_cache/3.9/builtins.data.json
ausmints_calculator/.mypy_cache/3.9/builtins.meta.json
ausmints_calculator/.mypy_cache/3.9/codecs.data.json
ausmints_calculator/.mypy_cache/3.9/codecs.meta.json
ausmints_calculator/.mypy_cache/3.9/genericpath.data.json
ausmints_calculator/.mypy_cache/3.9/genericpath.meta.json
ausmints_calculator/.mypy_cache/3.9/io.data.json
ausmints_calculator/.mypy_cache/3.9/io.meta.json
ausmints_calculator/.mypy_cache/3.9/math.data.json
ausmints_calculator/.mypy_cache/3.9/math.meta.json
ausmints_calculator/.mypy_cache/3.9/mmap.data.json
ausmints_calculator/.mypy_cache/3.9/mmap.meta.json
ausmints_calculator/.mypy_cache/3.9/posix.data.json
ausmints_calculator/.mypy_cache/3.9/posix.meta.json
ausmints_calculator/.mypy_cache/3.9/sys.data.json
ausmints_calculator/.mypy_cache/3.9/sys.meta.json
ausmints_calculator/.mypy_cache/3.9/types.data.json
ausmints_calculator/.mypy_cache/3.9/types.meta.json
ausmints_calculator/.mypy_cache/3.9/typing.data.json
ausmints_calculator/.mypy_cache/3.9/typing.meta.json
ausmints_calculator/.mypy_cache/3.9/typing_extensions.data.json
ausmints_calculator/.mypy_cache/3.9/typing_extensions.meta.json
ausmints_calculator/.mypy_cache/3.9/_typeshed/__init__.data.json
ausmints_calculator-0.2.1.dist-info/WHEEL
ausmints_calculator-0.2.1.dist-info/METADATA
ausmints_calculator-0.2.1.dist-info/RECORD
